db/__init__.py
db/column.py
db/db.py
db/query_templates.py
db/s3.py
db/table.py
db/utils.py
db/data/chinook.sqlite
db/queries/__init__.py
db/queries/mssql.py
db/queries/mysql.py
db/queries/postgres.py
db/queries/redshift.py
db/queries/sqlite.py
db/tests/__init__.py
db/tests/tests-mysql.py
db/tests/tests-postgres.py
db/tests/tests.py
db.py-0.5.3.dist-info/DESCRIPTION.rst
db.py-0.5.3.dist-info/METADATA
db.py-0.5.3.dist-info/RECORD
db.py-0.5.3.dist-info/WHEEL
db.py-0.5.3.dist-info/metadata.json
db.py-0.5.3.dist-info/top_level.txt
