Metadata-Version: 1.1
Name: db.py
Version: 0.5.3
Summary: a db package that doesn't suck
Home-page: https://github.com/yhat/db.py
Author: Greg Lamp
Author-email: greg@yhathq.com
License: BSD
Platform: UNKNOWN
Classifier: Development Status :: 4 - Beta
Classifier: License :: OSI Approved :: BSD License
Classifier: Programming Language :: Python :: 2
Classifier: Programming Language :: Python :: 2.6
Classifier: Programming Language :: Python :: 2.7
Classifier: Programming Language :: Python :: 3
Classifier: Programming Language :: Python :: 3.2
Classifier: Programming Language :: Python :: 3.3
Classifier: Programming Language :: Python :: 3.4
